ovpncp-0.1.5.dist-info/licenses/LICENSE
sciaiot/__init__.py
sciaiot/ovpncp/__init__.py
sciaiot/ovpncp/dependencies.py
sciaiot/ovpncp/log.yml
sciaiot/ovpncp/main.py
sciaiot/ovpncp/data/__init__.py
sciaiot/ovpncp/data/network.py
sciaiot/ovpncp/data/server.py
sciaiot/ovpncp/middlewares/azure_security.py
sciaiot/ovpncp/middlewares/azure_storage.py
sciaiot/ovpncp/routes/__init__.py
sciaiot/ovpncp/routes/client.py
sciaiot/ovpncp/routes/network.py
sciaiot/ovpncp/routes/server.py
sciaiot/ovpncp/scripts/client-connect.sh
sciaiot/ovpncp/scripts/client-disconnect.sh
sciaiot/ovpncp/utils/__init__.py
sciaiot/ovpncp/utils/iproute.py
sciaiot/ovpncp/utils/iptables.py
sciaiot/ovpncp/utils/openvpn.py
ovpncp-0.1.5.dist-info/METADATA
ovpncp-0.1.5.dist-info/WHEEL
ovpncp-0.1.5.dist-info/entry_points.txt
ovpncp-0.1.5.dist-info/top_level.txt
ovpncp-0.1.5.dist-info/RECORD
