Metadata-Version: 2.4
Name: ovpncp
Version: 0.1.5
Summary: OpenVPN Control Panel for Restricted Network.
Author-email: Nick Yao <ipaddict@outlook.com>
License: Apache License 2.0
Project-URL: Homepage, https://github.com/scia-iot
Project-URL: Source, https://github.com/scia-iot/ovpncp
License-File: LICENSE
Requires-Dist: cryptography
Requires-Dist: fastapi[all]
Requires-Dist: PyYAML
Requires-Dist: sqlmodel
Requires-Dist: uvicorn
Provides-Extra: security
Requires-Dist: python-jose[cryptography]; extra == "security"
Requires-Dist: types-python-jose; extra == "security"
Provides-Extra: azure
Requires-Dist: ovpncp[security]; extra == "azure"
Requires-Dist: azure-storage-blob; extra == "azure"
Dynamic: license-file
